README
README.md
SUPPORTED.md
__init__.py
centos-docker-mirror.py
centos-docker-mirror.tests.py
docker_image.py
docker_image.tests.py
docker_mirror.py
docker_mirror.pyi
docker_mirror.tests.py
dockerdir.py
dockerdir.pyi
dockerdir.tests.py
opensuse-docker-mirror.py
opensuse-docker-mirror.tests.py
setup.cfg
setup.py
ubuntu-docker-mirror.py
ubuntu-docker-mirror.tests.py
docker_mirror_packages_repo.egg-info/PKG-INFO
docker_mirror_packages_repo.egg-info/SOURCES.txt
docker_mirror_packages_repo.egg-info/dependency_links.txt
docker_mirror_packages_repo.egg-info/top_level.txt
scripts/filelist.py
scripts/filelist.pyi
scripts/mirrorlist.py
scripts/mirrorlist.pyi
scripts/mirrors.fedoraproject.org.py
scripts/mirrors.fedoraproject.org.pyi
scripts/repodata-fix.py