Metadata-Version: 2.1
Name: docker-mirror-packages-repo
Version: 1.7.7123
Summary: allow package installations to stay local at another docker container
Home-page: https://www.linkedin.com/in/gdraheim/
Author: Guido U. Draheim
Author-email: Guido.Draheim@gmx.de
License: CC0
Platform: UNKNOWN
